hypster/__init__.py
hypster/core.py
hypster/hp.py
hypster/hp_calls.py
hypster/py.typed
hypster/utils.py
hypster/hpo/__init__.py
hypster/hpo/optuna.py
hypster/hpo/types.py
hypster/integrations/__init__.py
hypster/integrations/optuna.py
hypster-0.3.8.dist-info/METADATA
hypster-0.3.8.dist-info/WHEEL
hypster-0.3.8.dist-info/licenses/LICENSE
hypster-0.3.8.dist-info/RECORD
