Metadata-Version: 2.4
Name: hypster
Version: 0.3.8
Summary: A flexible configuration system for Python projects
Project-URL: Homepage, https://github.com/gilad-rubin/hypster
Project-URL: Repository, https://github.com/gilad-rubin/hypster
Project-URL: Issues, https://github.com/gilad-rubin/hypster/issues
Author-email: Gilad Rubin <me@giladrubin.com>
License: MIT
License-File: LICENSE
Keywords: ai,configuration,machine-learning
Classifier: Development Status :: 4 - Beta
Classifier: Intended Audience :: Developers
Classifier: License :: OSI Approved :: MIT License
Classifier: Programming Language :: Python :: 3
Classifier: Programming Language :: Python :: 3.10
Classifier: Programming Language :: Python :: 3.11
Classifier: Programming Language :: Python :: 3.12
Requires-Python: >=3.10
Provides-Extra: dev
Requires-Dist: coverage[toml]>=7.0; extra == 'dev'
Requires-Dist: ipywidgets>=8.0.0; extra == 'dev'
Requires-Dist: mypy>=0.950; extra == 'dev'
Requires-Dist: pre-commit>=3.0; extra == 'dev'
Requires-Dist: pytest-cov>=4.0; extra == 'dev'
Requires-Dist: pytest>=6.0; extra == 'dev'
Requires-Dist: ruff>=0.1.0; extra == 'dev'
Provides-Extra: jupyter
Requires-Dist: ipywidgets>=8.0.0; extra == 'jupyter'
Provides-Extra: optuna
Requires-Dist: optuna>=3.6; extra == 'optuna'
